lotonumber/__init__.py
lotonumber/all_loto.py
lotonumber/analysis.py
lotonumber/analysis_basic.py
lotonumber/loto.py
lotonumber/loto6.py
lotonumber/loto6_analysis.py
lotonumber/loto7.py
lotonumber/loto7_analysis.py
lotonumber/loto_basic.py
lotonumber/miniloto.py
lotonumber/miniloto_analysis.py
lotonumber/read_loto6.py
lotonumber/read_loto7.py
lotonumber/read_miniloto.py
lotonumber/algo/__init__.py
lotonumber/algo/distribution.py
lotonumber/algo/scanty_number.py
lotonumber/data/loto6.csv
lotonumber/data/loto7.csv
lotonumber/data/miniloto.csv
lotonumber-0.0.7.dist-info/DESCRIPTION.rst
lotonumber-0.0.7.dist-info/METADATA
lotonumber-0.0.7.dist-info/RECORD
lotonumber-0.0.7.dist-info/WHEEL
lotonumber-0.0.7.dist-info/entry_points.txt
lotonumber-0.0.7.dist-info/metadata.json
lotonumber-0.0.7.dist-info/top_level.txt
