Metadata-Version: 2.0
Name: lotonumber
Version: 0.0.7
Summary: show a right number of loto.
Home-page: UNKNOWN
Author: solima
Author-email: UNKNOWN
License: GPL
Keywords: loto number
Platform: UNKNOWN
Requires-Dist: matplotlib
Requires-Dist: numpy
